Workbook

Sheet README
A1: Around the Word — Data Collection Workbook
A3: HOW THIS IS ORGANIZED
A4: One sheet per entity type — NOT one sheet per country.
A5: Every sheet has a country_code column. To see everything about Portugal, filter country_code = PT.
A7: Why not a sheet per country: each sheet here maps to one database table, so it imports as a single CSV.
A8: Sheet-per-country would mean merging 50+ tabs before anything could load, and would make cross-country
A9: questions ('which countries are missing visa info?') a manual crawl instead of a filter.
A11: HOW TO USE
A12: Row 1 = column headers. Do not rename or reorder them — they map to database fields.
A13: Row 2 = a grey italic example row. Delete it before importing, or leave it and skip row 2 on import.
A14: Start entering real data at row 3.
A16: COLOR KEY
B17: White = commodity data. Free from public datasets; safe to overwrite via import later.
B18: Yellow = curated. Your research and judgment. This is the actual product — never auto-overwritten.
B19: Orange = legally sensitive. Must have a source URL and a verified date. Never state as your own advice.
A21: FILL ORDER — suggested
A22: 1. Countries — add a row for every country you plan to cover, even if nothing else is filled yet.
A23: 2. Commodity_Facts + Cities — quick to fill from public sources, or skip and import later via script.
A24: 3. Guide_Items — the curated core. This is the part that takes real time and is worth the most.
A25: 4. Words then Phrases — words first, since phrases reference them.
A26: 5. Visas + Advisories — do these last per country, and re-check before launch. They go stale fastest.
A28: IDs
A29: Use short readable ids you make up yourself (pt-lisbon, es-food-01). The database will assign real UUIDs
A30: on import — these only need to be unique within this workbook so rows can reference each other.

Sheet Countries
A1: country_code | B1: name_common | C1: name_official | D1: primary_language_code | E1: content_status | F1: is_published | G1: visited_personally | H1: notes | I1: language_scope_na | J1: regional_group
A2: US | B2: United States | C2: United States of America | D2: en | E2: none | F2: FALSE | G2: TRUE | I2: FALSE
A3: GR | B3: Greece | C3: Hellenic Republic | D3: el | E3: partial | F3: FALSE | G3: TRUE | I3: FALSE | J3: schengen
A4: GB | B4: United Kingdom | C4: United Kingdom of Great Britain and Northern Ireland | D4: en | E4: none | F4: FALSE | G4: TRUE | I4: FALSE
A5: IT | B5: Italy | C5: Italian Republic | D5: it | E5: none | F5: FALSE | G5: TRUE | I5: FALSE
A6: ES | B6: Spain | C6: Kingdom of Spain | D6: es | E6: none | F6: FALSE | G6: TRUE | I6: FALSE
A7: IE | B7: Ireland | C7: Ireland | D7: en | E7: none | F7: FALSE | G7: TRUE | I7: TRUE
A8: GT | B8: Guatemala | C8: Republic of Guatemala | D8: es | E8: none | F8: FALSE | G8: TRUE | I8: FALSE
A9: NZ | B9: New Zealand | C9: New Zealand | D9: en | E9: none | F9: FALSE | G9: TRUE | I9: FALSE
A10: ID | B10: Indonesia | C10: Republic of Indonesia | D10: id | E10: none | F10: FALSE | G10: TRUE | I10: FALSE
A11: BR | B11: Brazil | C11: Federative Republic of Brazil | D11: pt | E11: none | F11: FALSE | G11: TRUE | I11: FALSE
A12: DE | B12: Germany | C12: Federal Republic of Germany | D12: de | E12: none | F12: FALSE | G12: TRUE | H12: FALSE | J12: schengen
A70: content_status: none | partial | complete — drives whether the app shows a full page or a coming-soon state.
A71: content_status: none | partial | complete (see thresholds in data architecture doc — now tab-presence based, not raw field counts)
A72: visited_personally: your own tracking. Useful for knowing which entries you can vouch for firsthand.
A74: language_scope_na: TRUE when full-country language content isn't the point (e.g. Canada — mostly English-speaking, language content deliberately scoped to Quebec French only). When TRUE, the Coverage sheet's 'ready' check ignores the words/phrases minimums for that country so the build-start trigger doesn't wait on content that was never meant to be complete.

Sheet Commodity_Facts
A1: country_code | B1: capital | C1: population | D1: currency_code | E1: currency_name | F1: calling_code | G1: official_languages | H1: latitude | I1: longitude | J1: flag_url | K1: source
A2: GR | B2: Athens | C2: 10400000 | D2: EUR | E2: Euro | F2: +30 | G2: Greek | H2: 37.9838 | I2: 23.7275 | J2: https://flagcdn.com/gr.svg | K2: Wikipedia; worldcountrydata.com; countrycode.org
A3: DE | B3: Berlin | C3: 83500000 | D3: EUR | E3: Euro | F3: +49 | G3: German | H3: 52.52 | I3: 13.405 | J3: https://flagcdn.com/de.svg | K3: Wikipedia; worldstats.io; geocountries.com
A4: BR | B4: Brasília | C4: 212000000 | D4: BRL | E4: Brazilian real | F4: +55 | G4: Portuguese | H4: -15.7939 | I4: -47.8828 | J4: https://flagcdn.com/br.svg | K4: Wikipedia; worldstats.io; worldcountrydata.com
A5: IE | B5: Dublin | C5: 5400000 | D5: EUR | E5: Euro | F5: +353 | G5: English, Irish | H5: 53.3498 | I5: -6.2603 | J5: https://flagcdn.com/ie.svg | K5: worldstats.io; worldcountrydata.com; countrycode.org
A61: This whole sheet is commodity data — eventually replaced by an automated import script.
A62: Filling it by hand now is fine, but don't spend much time here: it's the least valuable data in the workbook.
A63: official_languages: comma-separated if more than one.

Sheet Cities
A1: city_id | B1: country_code | C1: name | D1: population | E1: latitude | F1: longitude | G1: is_major | H1: is_featured | I1: why_featured
A2: ca-toronto | B2: CA | C2: Toronto | D2: 2794356 | E2: 43.6532 | F2: -79.3832 | G2: TRUE | H2: FALSE
A3: ca-vancouver | B3: CA | C3: Vancouver | D3: 662248 | E3: 49.2827 | F3: -123.1207 | G3: TRUE | H3: FALSE
A4: ca-montreal | B4: CA | C4: Montreal | D4: 1762949 | E4: 45.5019 | F4: -73.5674 | G4: TRUE | H4: FALSE
A5: ca-ottawa | B5: CA | C5: Ottawa | D5: 1017449 | E5: 45.4215 | F5: -75.6972 | G5: TRUE | H5: FALSE
A6: ca-quebec-city | B6: CA | C6: Quebec City | D6: 549459 | E6: 46.8139 | F6: -71.208 | G6: TRUE | H6: TRUE | I6: Best base for Quebec French immersion; historic walled Old Quebec is walkable
A7: gr-athens | B7: GR | C7: Athens | D7: 664046 | E7: 37.9838 | F7: 23.7275 | G7: TRUE | H7: TRUE | I7: Capital and largest city; natural base for a Greece itinerary — most-visited landmarks (Acropolis, Lycabettus) sit within Athens itself.
A8: de-berlin | B8: DE | C8: Berlin | D8: 3850809 | E8: 52.52 | F8: 13.405 | G8: TRUE | H8: FALSE
A9: de-munich | B9: DE | C9: Munich | D9: 1512491 | E9: 48.1351 | F9: 11.582 | G9: TRUE | H9: FALSE
A10: br-rio-de-janeiro | B10: BR | C10: Rio de Janeiro | D10: 6700000 | E10: -22.9068 | F10: -43.1729 | G10: TRUE | H10: FALSE
A11: br-salvador | B11: BR | C11: Salvador | D11: 2900000 | E11: -12.9777 | F11: -38.5016 | G11: TRUE | H11: FALSE
A12: ie-dublin | B12: IE | C12: Dublin | D12: 1388000 | E12: 53.3498 | F12: -6.2603 | G12: TRUE | H12: TRUE | I12: Capital and largest city; home to most of Ireland's major landmarks and the natural base for a first visit.
A13: ie-killarney | B13: IE | C13: Killarney | D13: 14504 | E13: 52.0599 | F13: -9.5044 | G13: FALSE | H13: FALSE
A14: ie-sligo | B14: IE | C14: Sligo | D14: 19199 | E14: 54.2766 | F14: -8.4761 | G14: FALSE | H14: FALSE
A15: ie-galway | B15: IE | C15: Galway | D15: 85910 | E15: 53.2707 | F15: -9.0568 | G15: TRUE | H15: FALSE
A61: is_major = mechanical (top cities by population). is_featured = your editorial pick.
A62: An import script may overwrite is_major. It must never touch is_featured or why_featured.

Sheet Leadership
A1: country_code | B1: title | C1: name | D1: since | E1: source_url | F1: last_verified
A2: CA | B2: Prime Minister | C2: Mark Carney | D2: 2025-03-14 | E2: https://www.pm.gc.ca/en/about | F2: 2026-08-04
A60: One row per country — the true top leader, in that country's own terms. title holds the real term ('Prime Minister', 'President', etc.), not a fixed head_of_state/head_of_government split. Skip ceremonial/constitutional-monarch roles entirely (e.g. Canada: Prime Minister only, not the King).
A61: Highest staleness risk in the workbook — nobody reports a wrong prime minister, they just quietly lose trust.
A62: The app must display last_verified. If keeping this current becomes a burden, dropping the feature beats showing stale data.

Sheet Guide_Items
A1: item_id | B1: country_code | C1: item_type | D1: title | E1: body | F1: severity_or_urgency | G1: applies_to | H1: months | I1: crowd_level | J1: sources | K1: verified_by
A2: ca-norm-01 | B2: CA | C2: tipping_norm | D2: Tipping is standard, not optional-feeling | E2: 15-20% of the pre-tax bill at restaurants, bars, and for taxis/rideshare is the norm; not leaving a tip reads as a real faux pas, not a minor oversight. | F2: important | G2: all | J2: radicalstorage.com; mdsvisa.com; rishiimmigration.ca
A3: ca-norm-02 | B3: CA | C3: punctuality_norm | D3: Punctuality expectations differ by setting | E3: Arrive 5-10 minutes early for work meetings/appointments. For social events like dinner parties, a few minutes late is fine, but more than 15 minutes late without a text or call is considered rude. | F3: fyi | G3: all | J3: mdsvisa.com
A4: ca-best-01 | B4: CA | C4: best_time | D4: Summer (June-August): warmest, busiest, most first-timer-friendly | E4: Peak season nationwide. Best weather for outdoor activities and city sightseeing, but also the most crowded and most expensive — book accommodations well ahead, especially near national parks. | H4: June,July,August | I4: peak | J4: adventure-life.com; holidify.com
A5: ca-best-02 | B5: CA | C5: best_time | D5: Shoulder season (May, September): the balance pick | E5: Mild weather, meaningfully fewer crowds than summer, and lower prices. Widely recommended as the best overall trade-off, especially for national parks and the Rockies. | H5: May,September | I5: moderate | J5: audleytravel.com; overthefallstoursniagara.com; afar.com
A6: ca-best-03 | B6: CA | C6: best_time | D6: Fall foliage: mid-September to mid-October | E6: Especially strong in Ontario and Eastern Canada. A distinct draw from the summer/shoulder-season crowd, with its own smaller peak around foliage timing. | H6: September,October | I6: moderate | J6: canadiantrainvacations.com
A7: ca-cuisine-01 | B7: CA | C7: cuisine | D7: Poutine | E7: Fries, cheese curds, and hot gravy; originated in rural Quebec in the 1950s. Quebec City and Montreal are considered the two "poutine capitals," each with local variations (smoked meat, pulled pork), though it's found nationwide. | J7: mustseespots.com; letsbuildup.org; insightvacations.com
A8: ca-cuisine-02 | B8: CA | C8: cuisine | D8: Maple syrup / cabane à sucre (sugar shack) | E8: Quebec produces the majority of the world's maple syrup. In early spring, sugar shacks in the Laurentians open for traditional maple-themed meals, including tire sur la neige (maple taffy poured onto snow). | J8: mustseespots.com; letsbuildup.org | K8: vegetarian-friendly
A9: ca-prep-01 | B9: CA | C9: prep | D9: Book national park lodging early; carry bear spray off main trails | E9: For Banff and similar parks, accommodations and campsites for peak summer (July-August) commonly sell out 10-12 months ahead. On trails that leave main paved paths, bear spray is standard precaution, not paranoia. | F9: recommended | G9: all | J9: aaa.com/tripcanvas; wereintherockies.com
A10: gr-best-01 | B10: GR | C10: best_time | D10: June and September: warm without peak-summer heat or crowds | E10: Best months to visit — warm, pleasant weather without the July/August peak-season crush. | H10: June,September | I10: moderate | J10: Colleen (personal experience)
A11: gr-tip-01 | B11: GR | C11: tipping_norm | D11: Tipping is optional and casual | E11: At tavernas, round up to the nearest euro or leave small change. At sit-down restaurants, 5-10% is typical. At fine dining, 10-15%. | F11: fyi | G11: all | J11: Colleen (personal experience)
A12: gr-cuisine-01 | B12: GR | C12: cuisine | D12: Gyros: cheap, widely available street food | E12: Normally chicken or pork, served with french fries inside the wrap. Eaten handheld like an ice cream cone — not folded and eaten like a taco, the way it's often served in the US. | J12: Colleen (personal experience)
A13: gr-cuisine-02 | B13: GR | C13: cuisine | D13: Tavernas commonly serve grilled meats with potatoes | E13: Sausage or other cuts of meat are a common taverna main course, typically served with potatoes on the side. | J13: Colleen (personal experience)
A14: de-best-01 | B14: DE | C14: best_time | D14: May, June, September, October: mild weather, fewer crowds | E14: Shoulder-season months — pleasant weather without peak summer heat or the biggest tourist crowds. | H14: May,June,September,October | I14: moderate | J14: Colleen (personal experience)
A15: de-best-02 | B15: DE | C15: best_time | D15: December: Christmas markets | E15: Christmas markets (Weihnachtsmärkte) are a genuinely distinct draw — mulled wine, seasonal stalls, and festive atmosphere in most major cities and towns. | H15: December | I15: moderate | J15: Colleen (personal experience)
A16: de-tip-01 | B16: DE | C16: tipping_norm | D16: Tipping is modest and situational | E16: 5-10% is typical for sit-down dining and taxis. For coffee, round up to the nearest euro. Tipping is not expected at all for fast food. | F16: fyi | G16: all | J16: Colleen (personal experience)
A17: br-festival-01 | B17: BR | C17: festival | D17: Lavagem do Bonfim | E17: Major religious/cultural festival in Salvador — thousands process roughly 8km from the Church of Conceição da Praia to the Bonfim Church, where baianas ceremonially wash the church steps with scented water. Blends Catholic and Candomblé traditions; second-biggest celebration in Bahia after Carnival. | H17: January | J17: Colleen (personal experience); en.wikipedia.org
A18: gr-transport-01 | B18: GR | C18: transport_norm | D18: Rideshare/taxi app: FREE NOW | E18: The app to use — formerly TaxiBeat, then Beat, rebranded to FREE NOW after a 2022 merger. Still commonly referred to by the old names, so don't be thrown if a local mentions "Beat." | F18: fyi | G18: all | J18: free-now.com; en.wikipedia.org
A19: id-transport-01 | B19: ID | C19: transport_norm | D19: Rideshare app: Grab (recommended over Gojek for foreign travelers) | E19: Indonesia's market is genuinely split between Grab and Gojek (~91% combined share, roughly even). Grab is the better pick specifically for US travelers because it reliably accepts foreign credit cards; Gojek frequently rejects them, requiring workarounds. | F19: fyi | G19: all | J19: mordorintelligence.com; cocodevelopmentgroup.com
A20: br-tip-01 | B20: BR | C20: tipping_norm | D20: No real tipping culture — it's baked into the bill instead | E20: At restaurants, the check typically includes an optional 10% service fee already added to the total — that fee functions as the tip. If service was genuinely unsatisfactory, you can ask to have it removed. Outside restaurants, tipping isn't a broad expectation the way it is in the US. | F20: fyi | G20: all | J20: Colleen (personal experience)
A21: br-transport-01 | B21: BR | C21: transport_norm | D21: Rideshare app: Uber | E21: Uber holds roughly half of Brazil's ride-hailing market — it's Uber's single largest market globally by driver count — with local rival 99 (Didi-backed) as the main alternative. Works normally for foreign travelers, no card-acceptance workarounds needed. | F21: fyi | G21: all | J21: gatewaytosouthamerica-newsblog.com; emergingmarkets.today
A22: br-best-01 | B22: BR | C22: best_time | D22: Amazon: May-September for wildlife viewing | E22: Dry season in the Amazon — lower water levels concentrate wildlife near remaining water sources and riverbanks, and trails that flood in the wet season become walkable. | H22: May,June,July,August,September | I22: moderate | J22: Colleen (personal experience)
A23: br-best-02 | B23: BR | C23: best_time | D23: Rest of Brazil: December-March | E23: Best window for Rio, Salvador, and most of the country outside the Amazon — warm, high season, coincides with Carnaval. | H23: December,January,February,March | I23: peak | J23: Colleen (personal experience)
A24: br-festival-02 | B24: BR | C24: festival | D24: Carnaval | E24: Brazil's biggest celebration — a movable feast tied to Easter (the Friday before Ash Wednesday through Fat Tuesday), typically landing in February or early March. Rio's version centers on Sambadrome samba-school parades plus hundreds of street blocos; Salvador's is built around trio elétrico sound trucks and axé music moving through the streets rather than a stadium parade. Expect most businesses to close, hotel prices to surge, and domestic flights/buses to sell out weeks ahead in Carnaval cities. | H24: February,March | J24: en.wikipedia.org; eskimo.travel
A25: br-cuisine-01 | B25: BR | C25: cuisine | D25: Feijoada | E25: Brazil's national dish — a slow-simmered black bean stew with various pork cuts and sausage, served with rice, sautéed collard greens (couve), farofa (toasted cassava flour), and orange slices. Traditionally a Wednesday and Saturday lunch dish specifically — many restaurants only serve it on those days, and it's heavy enough that it's rarely eaten for dinner. | J25: oliviascuisine.com; leblonsteakhouse.com; nowinrio.com
A26: br-cuisine-02 | B26: BR | C26: cuisine | D26: Pão de queijo | E26: Small, chewy cheese bread made with tapioca/cassava starch (naturally gluten-free). Originated in Minas Gerais but ubiquitous nationwide — a common breakfast and snack item, often sold fresh and warm at bakeries and even airports. | J26: Colleen (personal experience)
A27: br-cuisine-03 | B27: BR | C27: cuisine | D27: Moqueca | E27: Fish or seafood stew. The Bahian version (moqueca baiana) — the one you'll find in Salvador — is built on coconut milk and dendê (palm) oil, giving it a distinctive red-orange color and richness; this differs from the Espírito Santo version (moqueca capixaba), which skips the coconut milk and dendê for a more tomato-based broth. | J27: Colleen (personal experience)
A28: ie-cuisine-01 | B28: IE | C28: cuisine | D28: Irish breakfast ("full Irish") | E28: Fried eggs, bacon (closer to Canadian bacon than US-style), sausage, black and white pudding, grilled tomato, and toast — a substantial, common way to start the day, widely available at cafes and B&Bs. | J28: Colleen (personal experience)
A29: ie-cuisine-02 | B29: IE | C29: cuisine | D29: Guinness | E29: Dry stout, brewed in Dublin since 1759. Genuinely tastes different (fresher, creamier) poured in Ireland than the exported version elsewhere — a common enough observation that it's worth trying locally even if you're not usually a stout person. | J29: Colleen (personal experience)
A30: ie-cuisine-03 | B30: IE | C30: cuisine | D30: Irish stew | E30: Traditionally lamb or mutton, potatoes, carrots, onions, slow-simmered. A classic pub main, especially in cooler months. | J30: Colleen (personal experience)
A31: ie-cuisine-04 | B31: IE | C31: cuisine | D31: Soda bread | E31: Dense, slightly sweet bread leavened with baking soda instead of yeast (no rising time needed). Common at breakfast and served alongside stew. | J31: Colleen (personal experience)
A32: ie-tip-01 | B32: IE | C32: tipping_norm | D32: Tipping culture exists but isn't strong | E32: About 10% is appropriate at sit-down restaurants. For other services (cabs, casual counters), simply rounding up is common and sufficient — nowhere near the expectation level of US tipping norms. | F32: fyi | G32: all | J32: Colleen (personal experience)
A33: ie-best-01 | B33: IE | C33: best_time | D33: May, June, September | E33: Best months for weather — mild and comparatively dry by Irish standards, without the (relatively modest) peak-summer crowds of July/August. | H33: May,June,September | I33: moderate | J33: Colleen (personal experience)
A34: ie-festival-01 | B34: IE | C34: festival | D34: St. Patrick's Festival / Parade (Dublin) | E34: Ireland's national holiday and biggest celebration. The parade itself is always March 17, running from Parnell Square down O'Connell Street and over O'Connell Bridge to the Cuffe Street/Kevin Street junction — roughly half a million spectators line the route. The wider St. Patrick's Festival runs several days around it (typically March 14-17), with additional events across the city. | H34: March | J34: stpatricksfestival.ie
A35: de-festival-01 | B35: DE | C35: festival | D35: Oktoberfest (Munich) | E35: The world's largest folk festival — beer tents, fairground rides, and traditional Bavarian food at the Theresienwiese fairground. Despite the name, it actually runs mid-September through the first Sunday of October (moved earlier in the 1800s for better weather), lasting 16-18 days. Traditional dress (lederhosen for men, dirndls for women) is common but not required. Draws roughly 6-7 million visitors a year — book accommodations well ahead. | H35: September,October | I35: peak | J35: en.wikipedia.org; munich.travel
A60: This is the core curated sheet — practical basics, dress codes, best times, cuisine, history, prep advice. (Social norms/taboos are deferred to the V5 friend-verified social layer, not collected here — see item_type note below.)
A61: item_type: tipping_norm | punctuality_norm | transport_norm | dress | best_time | cuisine | history | festival | prep (each *_norm type is its own standalone type, not grouped under a shared 'practical_norm' bucket — so any one of them can be filtered and deleted across every country independently, without touching the others. New universal checks get their own new *_norm type the same way, rather than folding into an existing one.)
A62: severity_or_urgency: fyi | important | critical (for practical_norm/dress) · optional | recommended | required (for prep)
A63: months + crowd_level are only used when item_type = best_time. crowd_level: low | moderate | high | peak
A64: applies_to: all | women | men | or a specific site name (mainly for dress items)
A65: *_norm types (tipping_norm, punctuality_norm, transport_norm, ...) are for concrete, checkable-as-true-or-false items asked the same way for every country — not open-ended interpretive commentary. That kind of subjective social-norm/taboo content is intentionally deferred to friend verification in the social layer (V5), where disagreement between contributors is expected and handled, rather than asserted as a single fact now. transport_norm specifically: the app recommended for a TOURIST to use, not whichever has the biggest local market share — those can differ (e.g. foreign-card acceptance matters to a traveler, not to a local).
A66: Keeping all guide types in ONE sheet (rather than several) means one place to work and one import. Filter by item_type.

Sheet Explore
A1: poi_id | B1: country_code | C1: poi_type | D1: tags | E1: city_id | F1: name | G1: description | H1: dress_code | I1: visit_notes | J1: latitude | K1: longitude
A2: ca-niagara-falls | B2: CA | C2: landmark | F2: Niagara Falls | G2: Massive waterfall system on the Ontario/New York border; the Canadian side faces the wider, more famous Horseshoe Falls. | I2: Peak congestion is 11am-4pm; arrive before 10am or after 7:30pm to avoid crowds. Maid of the Mist boat tours run May-November only. May and September offer the best balance of good weather and manageable crowds. | J2: 43.0962 | K2: -79.0377
A3: ca-banff-np | B3: CA | C3: landmark | F3: Banff National Park | G3: Canada's oldest national park, in the Alberta Rockies; teal lakes (Lake Louise, Moraine Lake), mountain peaks, and abundant wildlife. | I3: Book lodging and campsites 10-12 months ahead for July-August. Carry bear spray on any trail that leaves the main paved paths. June and September are the best trade-off between wildlife visibility and crowd levels versus peak summer. | J3: 51.4968 | K3: -115.9281
A4: gr-acropolis | B4: GR | C4: landmark | E4: gr-athens | F4: Acropolis | G4: Ancient citadel above Athens, home to the Parthenon and other classical Greek monuments — visited together as one site. | J4: 37.9715 | K4: 23.7267
A5: gr-lycabettus | B5: GR | C5: landmark | E5: gr-athens | F5: Lycabettus Hill | G5: The highest point in Athens; funicular or walking trail to the summit for panoramic views over the city. | J5: 37.9779 | K5: 23.7761
A6: gr-sounion | B6: GR | C6: landmark | F6: Temple of Poseidon, Cape Sounion | G6: Coastal temple ruins roughly 70km from Athens, known for sunset views over the Aegean. | I6: Day trip from Athens. | J6: 37.6501 | K6: 24.0217
A7: gr-delphi | B7: GR | C7: landmark | F7: Temple of Apollo, Delphi | G7: Ancient sanctuary of the Oracle of Delphi, on the slopes of Mount Parnassus. | J7: 38.4824 | K7: 22.501
A8: gr-knossos | B8: GR | C8: landmark | F8: Palace of Minos, Knossos (Crete) | G8: Bronze Age Minoan palace complex near Heraklion, Crete. | J8: 35.2977 | K8: 25.1628
A9: gr-olympia | B9: GR | C9: landmark | F9: Ancient Olympia | G9: Site of the ancient Olympic Games and sanctuary of Zeus, in the Peloponnese. | J9: 37.6383 | K9: 21.63
A10: gr-panathenaic-stadium | B10: GR | C10: landmark | E10: gr-athens | F10: Panathenaic Stadium | G10: Historic marble stadium that hosted the first modern Olympic Games in 1896; built on the site of an ancient Greek stadium. | J10: 37.9683 | K10: 23.7411
A11: gr-parliament | B11: GR | C11: landmark | E11: gr-athens | F11: Greek Parliament / Changing of the Guard | G11: The Hellenic Parliament building in Syntagma Square; the ceremonial changing of the Evzones guard takes place out front. | J11: 37.9755 | K11: 23.7348
A12: gr-acropolis-museum | B12: GR | C12: landmark | E12: gr-athens | F12: Acropolis Museum | G12: Modern museum at the base of the Acropolis housing artifacts found on the site, including original Parthenon sculptures. | J12: 37.9686 | K12: 23.7285
A13: gr-ancient-agora | B13: GR | C13: landmark | E13: gr-athens | F13: Ancient Agora | G13: The central public space of ancient Athens — marketplace, civic, and social hub — with the well-preserved Temple of Hephaestus. | J13: 37.9755 | K13: 23.7222
A14: gr-national-archaeological-museum | B14: GR | C14: landmark | E14: gr-athens | F14: National Archaeological Museum | G14: Greece's largest archaeological museum, with major collections spanning prehistoric through Roman-era Greece. | J14: 37.9893 | K14: 23.7328
A15: gr-papia | B15: GR | C15: restaurant | D15: coffee,bar | E15: gr-athens | F15: Papia | G15: All-day cafe that turns into a bar at night; near Panathenaic Stadium in Pangrati. | J15: 37.9686 | K15: 23.7434
A16: gr-orizontes-lycabettus | B16: GR | C16: restaurant | D16: lunch,dinner | E16: gr-athens | F16: Orizontes Lycabettus | G16: Upscale restaurant at the summit of Lycabettus Hill; Mediterranean/Greek cuisine with panoramic views over Athens and the Acropolis. Reservations recommended. | J16: 37.9776 | K16: 23.7758
A17: gr-mountrichas | B17: GR | C17: restaurant | D17: breakfast,coffee | E17: gr-athens | F17: Mountrichas Bakery | G17: Traditional Athens bakery running since 1981; stone-milled flour, sourdough (no commercial yeast), wood-burning oven. Main branch in Pangrati. | H17: Small independent bakery — worth a quick check that it's still operating before planning a visit around it. | J17: 37.9686 | K17: 23.7448
A18: gr-meteora | B18: GR | C18: landmark | F18: Meteora Monasteries | G18: Eastern Orthodox monasteries built atop massive sandstone rock pillars near Kalambaka; UNESCO World Heritage Site. | J18: 39.7217 | K18: 21.6306
A19: gr-mystras | B19: GR | C19: landmark | F19: Mystras | G19: Byzantine fortress city and UNESCO World Heritage Site near Sparta, with well-preserved medieval churches, palaces, and monasteries. | J19: 37.068 | K19: 22.366
A20: gr-corinth-canal | B20: GR | C20: landmark | F20: Isthmus of Corinth | G20: Narrow land bridge connecting the Peloponnese to mainland Greece, cut through by the Corinth Canal; a popular bungee-jumping and photo stop. | J20: 37.9364 | K20: 22.9871
A21: gr-mount-olympus | B21: GR | C21: landmark | F21: Mount Olympus | G21: Greece's highest mountain (2,917m), mythological home of the twelve Olympian gods; a popular multi-day hiking destination. | J21: 40.0855 | K21: 22.3585
A22: gr-mercado | B22: GR | C22: restaurant | D22: lunch,dinner,bar | E22: gr-athens | F22: Mercado | G22: Mexican-style restaurant/bar in Monastiraki, at Ermou & Diomeias. | I22: Address listing shares a phone number/location with a 'Cantina Mejicana' entry on delivery apps — likely the same kitchen under related branding; worth confirming current name on arrival. | J22: 37.9758 | K22: 23.7276
A23: gr-six-dogs | B23: GR | C23: restaurant | D23: coffee,lunch,bar | E23: gr-athens | F23: 6 D.O.G.S | G23: All-day/all-night multi-space combining a club, bar, cafe, restaurant, and garden in one venue near Agia Irini Square. Relaxed cafe by day, live music/DJ venue by night. | J23: 37.9776 | K23: 23.7268
A24: gr-the-speakeasy | B24: GR | C24: restaurant | D24: bar | E24: gr-athens | F24: The Speakeasy | G24: Hidden cocktail bar behind an unmarked door near Syntagma Square, 1920s Prohibition theme with live jazz. | I24: Genuinely hard to find — no sign, ring the bell to enter. Part of the appeal, but worth knowing going in. | J24: 37.9773 | K24: 23.7328
A25: de-brandenburg-gate | B25: DE | C25: landmark | E25: de-berlin | F25: Brandenburg Gate | G25: Neoclassical monument at Pariser Platz; Berlin's most iconic landmark and former symbol of the city's Cold War division. | J25: 52.5163 | K25: 13.3777
A26: de-deutschlandmuseum | B26: DE | C26: landmark | E26: de-berlin | F26: Deutschlandmuseum | G26: Immersive history museum on Leipziger Platz covering 2,000 years of German history through life-size, walk-through recreations of historical settings (opened 2023). | J26: 52.5089 | K26: 13.3784
A27: de-natural-history-museum | B27: DE | C27: landmark | E27: de-berlin | F27: Museum für Naturkunde (Natural History Museum) | G27: Berlin's natural history museum; notable for one of the largest mounted dinosaur skeletons in the world. | J27: 52.5307 | K27: 13.3819
A28: de-mauerpark | B28: DE | C28: landmark | E28: de-berlin | F28: Mauerpark | G28: Former Berlin Wall death strip, now a park in Prenzlauer Berg. Sunday flea market plus the famous Bearpit Karaoke in the amphitheater, roughly spring through autumn. | I28: Karaoke starts around 3pm on Sundays, weather-dependent (no rain, roughly April-October) — check ahead if that's the draw. | J28: 52.5415 | K28: 13.4023
A29: de-berlin-wall | B29: DE | C29: landmark | E29: de-berlin | F29: Berlin Wall (Memorial / remaining sections) | G29: Remaining sections and memorial sites of the Berlin Wall; the Bernauer Straße memorial and the East Side Gallery (open-air mural gallery) are the two main places to see it. | J29: 52.535 | K29: 13.389
A30: de-glockenspiel | B30: DE | C30: landmark | E30: de-munich | F30: Rathaus-Glockenspiel | G30: Mechanical clock and carillon in the New Town Hall tower at Marienplatz; life-size figures re-enact scenes from Munich history, with shows at 11am and noon (plus 5pm March-October). | J30: 48.1374 | K30: 11.5755
A31: de-englischer-garten | B31: DE | C31: landmark | E31: de-munich | F31: Englischer Garten (English Garden) | G31: One of the world's largest urban public parks, larger than Central Park; includes the Eisbach surf wave and a Chinese Tower beer garden. | J31: 48.1642 | K31: 11.6056
A32: de-neuschwanstein | B32: DE | C32: landmark | F32: Schloss Neuschwanstein | G32: Fairy-tale 19th-century castle near Füssen in the Bavarian Alps, built for King Ludwig II; the inspiration for Disney's Sleeping Beauty castle. | J32: 47.5576 | K32: 10.7498
A33: de-museum-of-values | B33: DE | C33: landmark | E33: de-berlin | F33: Museum of Values (Museum für Werte) | G33: Non-profit running immersive, participatory exhibits exploring personal and societal values through interactive installations, active in Berlin since 2016. | I33: Best-guess match for a 2022 doorway-choice exhibit (freedom/security/tradition/equality) — not fully confirmed. Pop-up format with no fixed address or regular hours; past venues have included Markthalle Neun, old gymnasiums, churches, and even Teufelsberg. Check wertemuseum.de for current/upcoming locations rather than expecting a permanent site.
A34: de-charlottenburg-palace | B34: DE | C34: landmark | E34: de-berlin | F34: Charlottenburg Palace | G34: Berlin's largest palace — baroque and rococo former residence of the Prussian royal family, with extensive formal gardens. | J34: 52.521 | K34: 13.2954
A35: de-alexanderplatz | B35: DE | C35: landmark | E35: de-berlin | F35: Alexanderplatz | G35: Major public square and transit hub in central Berlin (Mitte); home to the TV Tower (Fernsehturm) and the World Clock. | J35: 52.5219 | K35: 13.4132
A36: de-berlin-zoo | B36: DE | C36: landmark | E36: de-berlin | F36: Berlin Zoological Garden | G36: Germany's oldest zoo (opened 1844) and one of the most species-rich zoos in the world. | J36: 52.5079 | K36: 13.3374
A37: br-christ-the-redeemer | B37: BR | C37: landmark | E37: br-rio-de-janeiro | F37: Christ the Redeemer | G37: Art Deco statue of Jesus Christ atop Corcovado mountain; one of the New Seven Wonders of the World, with panoramic views over Rio. | J37: -22.9519 | K37: -43.2105
A38: br-santa-teresa | B38: BR | C38: neighborhood | E38: br-rio-de-janeiro | F38: Santa Teresa | G38: Bohemian hillside neighborhood known for its narrow winding streets, artist studios, colonial-era mansions, and the historic Santa Teresa tram. | J38: -22.935 | K38: -43.1897
A39: br-aprazivel | B39: BR | C39: restaurant | D39: lunch,dinner | E39: br-rio-de-janeiro | F39: Aprazível | G39: Hilltop restaurant in Santa Teresa serving artisanal Brazilian cuisine (roots cuisine — moqueca, hearts of palm, Amazon fish) with sweeping treehouse-terrace views over the city and Guanabara Bay. | J39: -22.9327 | K39: -43.1892
A40: br-gurume-ipanema | B40: BR | C40: restaurant | D40: lunch,dinner | E40: br-rio-de-janeiro | F40: Gurumê (Ipanema) | G40: Contemporary Japanese restaurant in Ipanema — sushi, sashimi, and creative rolls. Part of a small Rio chain with several locations; this is the Ipanema branch specifically. | J40: -22.9838 | K40: -43.2016
A41: br-feira-sao-cristovao | B41: BR | C41: landmark | E41: br-rio-de-janeiro | F41: Feira de São Cristóvão | G41: Huge Northeastern-Brazilian culture fair (Feira Nordestina) in a stadium-like pavilion — nearly 700 stalls of food, handicrafts, clothing, and regional products, plus live forró/baião music and dancing. Runs Friday through Sunday. | I41: Best on weekends for the full atmosphere and live music; weekdays are calmer and cheaper but miss the party energy. | J41: -22.8983 | K41: -43.2225
A42: br-pelourinho | B42: BR | C42: neighborhood | E42: br-salvador | F42: Pelourinho | G42: Salvador's UNESCO World Heritage historic center — colorful colonial architecture, cobblestone streets, and the largest collection of colonial-era buildings in Latin America. | J42: -12.9714 | K42: -38.5108
A43: br-farol-da-barra-beach | B43: BR | C43: landmark | E43: br-salvador | F43: Praia do Farol da Barra | G43: Popular city beach in the Barra neighborhood, right at the point where Salvador's bay meets the open Atlantic. | J43: -13.0089 | K43: -38.5323
A44: br-farol-da-barra-lighthouse | B44: BR | C44: landmark | E44: br-salvador | F44: Farol da Barra (lighthouse) | G44: The oldest lighthouse in the Americas, at Forte de Santo Antônio da Barra; houses the Nautical Museum of Bahia. | J44: -13.0106 | K44: -38.5321
A45: br-mam-ba | B45: BR | C45: landmark | E45: br-salvador | F45: MAM-BA (Museu de Arte Moderna da Bahia) | G45: Modern art museum in the historic Solar do Unhão complex on the bay, with a sculpture garden and sunset waterfront views. Known for "Jam no MAM," a Saturday-evening music session mixing samba, baião, jazz, and other genres. | J45: -12.9791 | K45: -38.5157
A46: br-little-england-cafe | B46: BR | C46: restaurant | D46: coffee,breakfast | E46: br-salvador | F46: Little England Café | G46: English-style café in Pelourinho — coffee, tea, and an Afternoon Tea Tower experience served for two by reservation. | I46: Book in advance — timed tickets sell out, especially in summer. | J46: -12.9714 | K46: -38.5108
A47: br-cuco-bistro | B47: BR | C47: restaurant | D47: lunch,dinner | E47: br-salvador | F47: Cuco Bistrô | G47: Northeastern Bahian cuisine with a Mediterranean touch, seafood-focused, plus one of Salvador's best cachaça collections. Live music some evenings. | J47: -12.9736 | K47: -38.5099
A48: br-recôncavo-culinaria | B48: BR | C48: restaurant | D48: lunch,dinner | E48: br-salvador | F48: Recôncavo Culinária | G48: Traditional Bahian and Recôncavo-region cuisine in Barra — moqueca, seafood, cocktails. | J48: -13.0089 | K48: -38.528
A49: br-kitanda-gastrobar | B49: BR | C49: restaurant | D49: lunch,dinner | E49: br-salvador | F49: Kitanda Gastrobar (Farol da Barra) | G49: Oceanfront Bahian restaurant/bar right on the Farol da Barra boardwalk, with strong vegan/vegetarian options alongside seafood and moqueca. | J49: -13.0089 | K49: -38.5323
A50: br-odoya | B50: BR | C50: restaurant | D50: lunch,dinner | E50: br-salvador | F50: Odoyá | G50: Traditional Bahian seafood restaurant in Pelourinho, named for the greeting to Yemanjá (orixá of the sea). | J50: -12.9736 | K50: -38.5099
A51: br-atelier-enock | B51: BR | C51: landmark | E51: br-salvador | F51: Atelier do Artista Enock (Ateliê Enock Silva) | G51: Working studio and gallery of artist Enock Silva in Pelourinho, one of several artist ateliers open to visitors in the historic center. | J51: -12.9714 | K51: -38.5108
A52: ie-guinness-storehouse | B52: IE | C52: landmark | E52: ie-dublin | F52: Guinness Storehouse | G52: Guinness's original brewery site (St. James's Gate) turned multi-floor visitor experience, ending at the Gravity Bar with a 360° view over Dublin and a pint included with admission. | J52: 53.3419 | K52: -6.2867
A53: ie-trinity-college-library | B53: IE | C53: landmark | E53: ie-dublin | F53: Trinity College Old Library & Book of Kells | G53: Trinity's Old Library (the Long Room) alongside the Book of Kells exhibition — an illuminated medieval manuscript gospel book. Functions as both a working library and the de facto museum experience most visitors mean by "Trinity College." | I53: Book in advance — timed tickets sell out, especially in summer. | J53: 53.3438 | K53: -6.2546
A54: ie-temple-bar | B54: IE | C54: neighborhood | E54: ie-dublin | F54: Temple Bar | G54: Dublin's cobblestoned cultural/nightlife quarter — pubs, live trad music, galleries. Touristy and pricier than elsewhere in Dublin, but the concentration of live music makes it worth at least a stop. | J54: 53.3454 | K54: -6.2637
A55: ie-cliffs-of-moher | B55: IE | C55: landmark | F55: Cliffs of Moher | G55: Dramatic 214m sea cliffs on the County Clare coast, one of Ireland's most-visited natural landmarks. Commonly done as a day trip from Galway (roughly 1.5-2 hours each way), which is why it's grouped here as regional rather than tagged to any single city. | J55: 52.9715
A56: ie-shoot-the-crows | B56: IE | C56: restaurant | D56: bar | E56: ie-sligo | F56: Shoot the Crows | G56: One of Sligo's oldest pubs (dating to 1878), known for live traditional music and a large window painting that changes monthly, usually depicting a mythological or mystical figure. | J56: 54.2704
A57: ie-maeves-cairn | B57: IE | C57: landmark | E57: ie-sligo | F57: Queen Maeve's Cairn (Knocknarea) | G57: Massive unexcavated Neolithic cairn (c. 3000 BC) atop Knocknarea mountain, legendarily said to be the burial site of Queen Maeve (Medb) of Connacht — though the cairn actually predates her legend by millennia. | I57: Roughly 40-minute uphill walk from the car park; rough path, real walking shoes recommended. | J57: 54.2679
A58: ie-yeats-grave | B58: IE | C58: landmark | E58: ie-sligo | F58: W.B. Yeats's grave (Drumcliffe) | G58: Yeats is buried in the churchyard of St. Columba's Church in Drumcliffe, at the foot of Benbulben mountain, per his own wishes as stated in his poem "Under Ben Bulben." Simple headstone bearing the poem's closing epitaph. | J58: 54.3346
A61: dress_code and visit_notes are the genuinely useful fields — the stuff a guidebook lists but doesn't tell you honestly.
A62: city_id must match an id from the Cities sheet. Leave blank if the point of interest isn't tied to one city (a whole-region site like Delphi or Olympia, for instance).
A63: poi_type: landmark | restaurant | neighborhood, extensible — add new types the same way tipping_norm/punctuality_norm were added to Guide_Items. Each type is independently filterable and deletable across every country.
A64: tags (restaurant-type POIs only): comma-separated from breakfast, lunch, dinner, coffee, bar. A venue that's a cafe by day and a bar by night gets both tags on one row — no need to split it into separate entries or force a single label that misrepresents the place.
K65: -9.4309
K66: -8.4761
K67: -8.5717
K68: -8.4919
A69: br-brazillink | B69: BR | C69: activity | E69: br-salvador | F69: BrazilLink (Portuguese classes) | G69: Portuguese language school for foreigners in the Barra neighborhood, offering group and private classes plus cultural activities (dance, capoeira, guided tours). All three of Salvador's foreigner-focused Portuguese schools are in Barra. | J69: -13.0089 | K69: -38.528

Sheet Categories
A1: category_slug | B1: name | C1: parent_slug | D1: sort_order
A2: food-cooking | B2: Cooking | C2: food | D2: 1
A3: greetings | B3: Greetings & Courtesy | D3: 1
A4: travel-basics | B4: Travel Basics | D4: 2
A62: Shared across ALL countries — fill this in once, not per country.
A63: parent_slug blank = top-level category. Otherwise it must match another row's category_slug.
A64: Your existing list: food (cooking, grocery-shopping), shopping (malls, souvenirs), hiking-outdoors, family,
A65: aesthetics, transportation (airports, bus-stations, taxis), houses, museums, music, occupations,
A66: speaking-casually, celebrations (wedding, graduation, birthday, holiday), tv-movies, parties.

Sheet Words
A1: word_id | B1: country_code | C1: language_code | D1: lemma | E1: translation | F1: part_of_speech | G1: gender | H1: pronunciation | I1: ipa | J1: category_slugs | K1: usage_note | L1: difficulty
A2: ca-word-hello | B2: CA | C2: fr | D2: Bonjour | E2: Hello | F2: interjection | H2: bohn-ZHOOR | I2: bɔ̃.ʒuʁ | J2: greetings | K2: Standard greeting used throughout the day; also works as "good morning/afternoon." | L2: beginner
A3: ca-word-goodbye | B3: CA | C3: fr | D3: Au revoir | E3: Goodbye | F3: interjection | H3: oh ruh-VWAHR | I3: o ʁə.vwaʁ | J3: greetings | K3: Formal-neutral goodbye; fine in any situation. | L3: beginner
A4: ca-word-please | B4: CA | C4: fr | D4: S'il vous plaît | E4: Please | F4: interjection | H4: seel voo PLEH | I4: sil vu plɛ | J4: greetings | K4: Formal/polite "please" — safe default with strangers, service staff, elders. | L4: beginner
A5: ca-word-thankyou | B5: CA | C5: fr | D5: Merci | E5: Thank you | F5: interjection | H5: mehr-SEE | I5: mɛʁ.si | J5: greetings | K5: Universal thank you; add "beaucoup" (merci beaucoup) to emphasize. | L5: beginner
A6: gr-word-hello | B6: GR | C6: el | D6: Γεια σας | E6: Hello | F6: interjection | H6: YAH sahs | I6: ˈʝa sas | J6: greetings | K6: Formal/plural greeting — safest with strangers. Informal singular is "Γεια σου" (ya soo). | L6: beginner
A7: gr-word-goodbye | B7: GR | C7: el | D7: Αντίο | E7: Goodbye | F7: interjection | H7: ahn-DEE-oh | I7: anˈdio | J7: greetings | K7: "Γεια σου/σας" also doubles as a casual goodbye, similar to how it works as hello. | L7: beginner
A8: gr-word-please | B8: GR | C8: el | D8: Παρακαλώ | E8: Please | F8: interjection | H8: pah-rah-kah-LOH | I8: parakaˈlo | J8: greetings | K8: Also used to mean "you're welcome" in response to thanks. | L8: beginner
A9: gr-word-thankyou | B9: GR | C9: el | D9: Ευχαριστώ | E9: Thank you | F9: interjection | H9: ef-hah-ree-STOH | I9: efxariˈsto | J9: greetings | K9: Universal thank you. | L9: beginner
A10: de-word-hello | B10: DE | C10: de | D10: Hallo | E10: Hello | F10: interjection | H10: HAH-loh | I10: ˈhaːloː | J10: greetings | K10: Informal and universally fine. "Guten Tag" (GOO-ten tahk) is the more formal alternative with strangers/service staff. | L10: beginner
A11: de-word-goodbye | B11: DE | C11: de | D11: Auf Wiedersehen | E11: Goodbye | F11: interjection | H11: owf VEE-der-zayn | I11: aʊf ˈviːdɐzeːən | J11: greetings | K11: Formal/safe default. "Tschüss" (chuess) is the common informal goodbye among friends or casual service interactions. | L11: beginner
A12: de-word-please | B12: DE | C12: de | D12: Bitte | E12: Please | F12: interjection | H12: BIT-uh | I12: ˈbɪtə | J12: greetings | K12: Also means "you're welcome" and "pardon?/come again?" depending on context — genuinely does triple duty. | L12: beginner
A13: de-word-thankyou | B13: DE | C13: de | D13: Danke | E13: Thank you | F13: interjection | H13: DAHN-kuh | I13: ˈdaŋkə | J13: greetings | K13: Add "schön" (Danke schön) or "sehr" (Danke sehr) for more emphasis. | L13: beginner
A14: de-word-excuseme | B14: DE | C14: de | D14: Entschuldigung | E14: Excuse me / Sorry | F14: interjection | H14: ent-SHOOL-dih-gung | I14: ɛntˈʃʊldɪɡʊŋ | J14: travel-basics | K14: Long word but extremely high-mileage — use it to get attention, apologize, or squeeze past someone. | L14: beginner
A15: de-word-yes | B15: DE | C15: de | D15: Ja | E15: Yes | F15: adverb | H15: yah | I15: jaː | J15: travel-basics | L15: beginner
A16: de-word-no | B16: DE | C16: de | D16: Nein | E16: No | F16: adverb | H16: nine | I16: naɪn | J16: travel-basics | L16: beginner
A17: de-word-water | B17: DE | C17: de | D17: Wasser | E17: Water | F17: noun | G17: n | H17: VAH-ser | I17: ˈvasɐ | J17: travel-basics | K17: Restaurants default to sparkling ("mit Gas") unless you specify "ohne Gas" (still/flat) or "Leitungswasser" (tap water, not always offered). | L17: beginner
A18: de-word-bathroom | B18: DE | C18: de | D18: Toilette | E18: Bathroom / Toilet | F18: noun | G18: f | H18: toy-LET-uh | I18: toaˈlɛtə | J18: travel-basics | K18: Public restrooms are often pay-to-use (small coin) — worth keeping change on hand. | L18: beginner
A19: de-word-trainstation | B19: DE | C19: de | D19: Bahnhof | E19: Train station | F19: noun | G19: m | H19: BAHN-hohf | I19: ˈbaːnhoːf | J19: travel-basics | L19: beginner
A20: br-word-hello | B20: BR | C20: pt | D20: Olá | E20: Hello | F20: interjection | H20: oh-LAH | I20: oˈla | J20: greetings | K20: Universal and safe. "Oi" is the extremely common informal alternative — arguably more frequent in everyday speech than "Olá." | L20: beginner
A21: br-word-goodbye | B21: BR | C21: pt | D21: Tchau | E21: Goodbye | F21: interjection | H21: chow | I21: tʃaw | J21: greetings | K21: Casual but used almost everywhere in Brazil, including with strangers — not limited to close friends the way "bye" can feel in English. | L21: beginner
A22: br-word-please | B22: BR | C22: pt | D22: Por favor | E22: Please | F22: interjection | H22: por fah-VOR | I22: poʁ faˈvoʁ | J22: greetings | L22: beginner
A23: br-word-thankyou | B23: BR | C23: pt | D23: Obrigado | E23: Thank you | F23: interjection | H23: oh-bree-GAH-doo | I23: obɾiˈɡadu | J23: greetings | K23: Agrees with the SPEAKER's gender, not the listener's — a man says "obrigado," a woman says "obrigada," regardless of who they're thanking. | L23: beginner
A24: br-word-excuseme | B24: BR | C24: pt | D24: Com licença | E24: Excuse me | F24: interjection | H24: kohm lee-SEN-sah | I24: kõ liˈsẽsa | J24: travel-basics | K24: For passing by, getting attention, or asking permission. Different from "desculpa" (sorry/apology) — Portuguese splits what English does with one word into two. | L24: beginner
A25: br-word-yes | B25: BR | C25: pt | D25: Sim | E25: Yes | F25: adverb | H25: seeng | I25: sĩ | J25: travel-basics | L25: beginner
A26: br-word-no | B26: BR | C26: pt | D26: Não | E26: No | F26: adverb | H26: now (nasal) | I26: nɐ̃w | J26: travel-basics | L26: beginner
A27: br-word-water | B27: BR | C27: pt | D27: Água | E27: Water | F27: noun | G27: f | H27: AH-gwah | I27: ˈaɡwa | J27: travel-basics | K27: "Água com gás" is sparkling, "água sem gás" is still — worth specifying since restaurants may ask. | L27: beginner
A28: br-word-bathroom | B28: BR | C28: pt | D28: Banheiro | E28: Bathroom / Toilet | F28: noun | G28: m | H28: bahn-YAY-roo | I28: bɐˈɲeɾu | J28: travel-basics | L28: beginner
A29: br-word-trainstation | B29: BR | C29: pt | D29: Estação de trem | E29: Train station | F29: noun | G29: f | H29: es-tah-SOWN jee trehm | I29: estɐˈsɐ̃w dʒi trẽj | J29: travel-basics | L29: beginner
A61: Words and phrases are SEPARATE — a word is a dictionary entry, a phrase is a sentence made of tokens.
A62: Organized by country, not language: Portugal and Brazil get separate rows even though both are Portuguese.
A63: category_slugs: comma-separated if the word belongs to several.
A64: ipa is optional now but worth capturing where easy — it's what the future pronunciation-rules exercise needs.
A65: difficulty: 1-5, your judgment, for later game sequencing. Leave blank if unsure.

Sheet Phrases
A1: phrase_id | B1: country_code | C1: language_code | D1: category_slug | E1: text | F1: translation | G1: literal_translation | H1: pronunciation | I1: formality | J1: usage_note | K1: maskable_words | L1: sort_order
A2: ca-phrase-good-morning | B2: CA | C2: fr | D2: greetings | E2: Bon matin | F2: Good morning | G2: Good morning | H2: bohn mah-TAN | I2: informal | J2: Distinctly Quebec French — standard/France French has no separate morning greeting and just uses "Bonjour" until early evening. | L2: 1
A3: ca-phrase-good-afternoon | B3: CA | C3: fr | D3: greetings | E3: Bonjour | F3: Good afternoon | G3: Good day | H3: bohn-ZHOOR | I3: either | J3: French doesn't distinguish morning/afternoon the way English does — "Bonjour" covers both, used from morning until roughly 6pm. | L3: 2
A4: ca-phrase-good-evening | B4: CA | C4: fr | D4: greetings | E4: Bonsoir | F4: Good evening | G4: Good evening | H4: bohn-SWAHR | I4: either | J4: Used as a greeting after roughly 6pm. | L4: 3
A5: ca-phrase-good-night | B5: CA | C5: fr | D5: greetings | E5: Bonne nuit | F5: Good night | G5: Good night | H5: bun NWEE | I5: either | J5: Used when parting for the night or going to bed — not a greeting used on meeting someone in the evening (that's "Bonsoir"). | L5: 4
A6: gr-phrase-good-morning | B6: GR | C6: el | D6: greetings | E6: Καλημέρα | F6: Good morning | G6: Good day | H6: kah-lee-MEH-rah | I6: either | J6: Used from sunrise until roughly noon or early afternoon. | L6: 1
A7: gr-phrase-good-afternoon | B7: GR | C7: el | D7: greetings | E7: Καλησπέρα | F7: Good afternoon | G7: Good evening | H7: kah-lee-SPEH-rah | I7: either | J7: Greek has no distinct "good afternoon" term — this word covers both afternoon and evening, typically starting around noon to mid-afternoon. | L7: 2
A8: gr-phrase-good-evening | B8: GR | C8: el | D8: greetings | E8: Καλησπέρα | F8: Good evening | G8: Good evening | H8: kah-lee-SPEH-rah | I8: either | J8: Same word as "good afternoon" in Greek — no separate evening-specific greeting. | L8: 3
A9: gr-phrase-good-night | B9: GR | C9: el | D9: greetings | E9: Καληνύχτα | F9: Good night | G9: Good night | H9: kah-lee-NEEKH-tah | I9: either | J9: Only used when parting or going to bed — not used as a greeting on meeting someone in the evening (that's "Καλησπέρα"). | L9: 4
A10: de-phrase-good-morning | B10: DE | C10: de | D10: greetings | E10: Guten Morgen | F10: Good morning | G10: Good morning | H10: GOO-ten MOR-gen | I10: either | J10: Used until roughly 10-11am. | L10: 1
A11: de-phrase-good-afternoon | B11: DE | C11: de | D11: greetings | E11: Guten Tag | F11: Good afternoon | G11: Good day | H11: GOO-ten tahk | I11: either | J11: German's general daytime greeting — covers what English splits into "good afternoon," used from late morning into early evening. | L11: 2
A12: de-phrase-good-evening | B12: DE | C12: de | D12: greetings | E12: Guten Abend | F12: Good evening | G12: Good evening | H12: GOO-ten AH-bent | I12: either | J12: Used from roughly early evening onward. | L12: 3
A13: de-phrase-good-night | B13: DE | C13: de | D13: greetings | E13: Gute Nacht | F13: Good night | G13: Good night | H13: GOO-tuh nakht | I13: either | J13: Parting/bedtime only — not a greeting used on meeting someone in the evening (that's "Guten Abend"). | L13: 4
A14: de-phrase-speak-english | B14: DE | C14: de | D14: travel-basics | E14: Sprechen Sie Englisch? | F14: Do you speak English? | G14: Speak you English? | H14: SHPREH-khen zee ENG-lish | I14: formal | J14: Formal "Sie" form — the safe default with strangers and service staff. | K14: Englisch | L14: 5
A15: de-phrase-dont-understand | B15: DE | C15: de | D15: travel-basics | E15: Ich verstehe nicht | F15: I don't understand | G15: I understand not | H15: ikh fer-SHTAY-uh nikht | I15: either | L15: 6
A16: de-phrase-where-bathroom | B16: DE | C16: de | D16: travel-basics | E16: Wo ist die Toilette? | F16: Where is the bathroom? | G16: Where is the toilet? | H16: voh ist dee toy-LET-uh | I16: either | K16: Toilette | L16: 7
A17: de-phrase-how-much | B17: DE | C17: de | D17: travel-basics | E17: Wie viel kostet das? | F17: How much does this cost? | G17: How much costs that? | H17: vee feel KOS-tet dahs | I17: either | L17: 8
A18: de-phrase-bill-please | B18: DE | C18: de | D18: travel-basics | E18: Die Rechnung, bitte | F18: The check, please | G18: The bill, please | H18: dee REKH-nung, BIT-uh | I18: either | J18: Restaurants don't bring the check unprompted — you have to ask for it. | K18: Rechnung | L18: 9
A19: de-phrase-id-like | B19: DE | C19: de | D19: travel-basics | E19: Ich hätte gern... | F19: I would like... | G19: I would-have gladly... | H19: ikh HET-uh gairn | I19: either | J19: Standard polite way to order food/drinks — more natural than "Ich will" ("I want"), which can sound blunt. | L19: 10
A20: de-phrase-cheers | B20: DE | C20: de | D20: travel-basics | E20: Prost! | F20: Cheers! | G20: Cheers! | H20: prohst | I20: informal | J20: The toast — make eye contact while clinking glasses; skipping eye contact is considered mildly bad luck/rude. | L20: 11
A21: br-phrase-good-morning | B21: BR | C21: pt | D21: greetings | E21: Bom dia | F21: Good morning | G21: Good day | H21: bohm JEE-ah | I21: either | J21: Used from sunrise until roughly noon. | L21: 1
A22: br-phrase-good-afternoon | B22: BR | C22: pt | D22: greetings | E22: Boa tarde | F22: Good afternoon | G22: Good afternoon | H22: BOH-ah TAR-jee | I22: either | J22: Used from around noon until sunset. | L22: 2
A23: br-phrase-good-evening | B23: BR | C23: pt | D23: greetings | E23: Boa noite | F23: Good evening | G23: Good night | H23: BOH-ah NOY-chee | I23: either | J23: Same word as "good night" in Portuguese — used both as a greeting after sunset and when parting for the night. Context makes it clear which is meant. | L23: 3
A24: br-phrase-good-night | B24: BR | C24: pt | D24: greetings | E24: Boa noite | F24: Good night | G24: Good night | H24: BOH-ah NOY-chee | I24: either | J24: Identical to "good evening" — Portuguese doesn't distinguish the greeting from the farewell the way English does. | L24: 4
A25: br-phrase-speak-english | B25: BR | C25: pt | D25: travel-basics | E25: Você fala inglês? | F25: Do you speak English? | G25: You speak English? | H25: voh-SAY FAH-lah een-GLES | I25: either | K25: inglês | L25: 5
A26: br-phrase-dont-understand | B26: BR | C26: pt | D26: travel-basics | E26: Eu não entendo | F26: I don't understand | G26: I not understand | H26: eh-oo now en-TEN-doo | I26: either | L26: 6
A27: br-phrase-where-bathroom | B27: BR | C27: pt | D27: travel-basics | E27: Onde fica o banheiro? | F27: Where is the bathroom? | G27: Where is-located the bathroom? | H27: OHN-jee FEE-kah oo bahn-YAY-roo | I27: either | K27: banheiro | L27: 7
A28: br-phrase-how-much | B28: BR | C28: pt | D28: travel-basics | E28: Quanto custa isso? | F28: How much does this cost? | G28: How-much costs this? | H28: KWAHN-too KOOS-tah EE-soo | I28: either | L28: 8
A29: br-phrase-bill-please | B29: BR | C29: pt | D29: travel-basics | E29: A conta, por favor | F29: The check, please | G29: The bill, please | H29: ah KOHN-tah por fah-VOR | I29: either | K29: conta | L29: 9
A30: br-phrase-id-like | B30: BR | C30: pt | D30: travel-basics | E30: Eu queria... | F30: I would like... | G30: I wanted... | H30: eh-oo keh-REE-ah | I30: either | J30: Literally past tense ("I wanted"), but functions as the standard polite way to order or request something — softer than "eu quero" ("I want"), similar to how English uses "I would like" instead of a blunt "I want." | L30: 10
A31: br-phrase-cheers | B31: BR | C31: pt | D31: travel-basics | E31: Saúde! | F31: Cheers! | G31: Health! | H31: sah-OO-jee | I31: informal | J31: The standard toast — literally "health." | L31: 11
A32: ie-phrase-slainte | B32: IE | C32: ga | D32: greetings | E32: Sláinte | F32: Cheers! | G32: Health! | H32: SLAWN-cha | I32: informal | J32: The standard toast — literally "health," same root idea as Portuguese's "Saúde." | L32: 1
A33: ie-phrase-cead-mile-failte | B33: IE | C33: ga | D33: greetings | E33: Céad míle fáilte | F33: A hundred thousand welcomes | G33: Hundred thousand welcome | H33: kayd MEE-luh FAWL-cha | I33: either | J33: Traditional warm-welcome phrase — commonly seen on signage and spoken as a greeting, especially in tourist-facing contexts. Not something you'd hear in casual daily conversation the way "hello" gets used. | L33: 2
A34: ie-phrase-craic | B34: IE | C34: en | D34: greetings | E34: Craic | F34: Fun / good times / banter | G34: Fun/good times | H34: crack | I34: informal | J34: Not actually Irish-language — Hiberno-English slang (roots in Scottish/Old English "crack"), spelled with an Irish-looking "c" as a cultural nod. Extremely common — "What's the craic?" is a standard casual greeting ("what's up"), "good craic" describes a fun time or person. | L34: 3
A35: ie-phrase-failte | B35: IE | C35: ga | D35: greetings | E35: Fáilte | F35: Welcome | G35: Welcome | H35: FAWL-cha | I35: either | J35: Genuinely Irish, and extremely common on signage — you'll see it everywhere ("Céad míle fáilte" is this word intensified, literally "a hundred thousand welcomes"). | L35: 4
A61: maskable_words: which words in this phrase are worth blanking out in a fill-in-the-blank exercise.
A62: Comma-separated, using the exact form as it appears in the phrase (ficam, not ficar).
A63: Rule of thumb: blank content words and tricky grammar, not articles or punctuation. If blanking it teaches
A64: nothing ('Onde ficam ___ talheres?'), leave it out. This is a teaching judgment, not a mechanical one.
A65: A tokenizer will split the phrase automatically on import; this column just captures which tokens matter.
A66: formality: formal | informal | either

Sheet Visas
A1: destination_country_code | B1: nationality_country_code | C1: summary | D1: official_url | E1: last_verified | F1: notes | G1: prohibited_on_entry | H1: prohibited_on_exit | I1: application_url
A2: CA | B2: US | C2: No visa or Electronic Travel Authorization (eTA) required for US citizens entering Canada by air, land, or sea. A valid US passport is required; stays of up to 6 months are typically permitted for tourism. US lawful permanent residents (green card holders) are also exempt, though required documents differ by mode of travel. | D2: https://www.canada.ca/en/immigration-refugees-citizenship/services/visit-canada/entry-requirements-country.html | E2: 2026-08-04 | F2: US citizens are a specific exemption — most other visa-exempt nationalities (UK, EU, etc.) still need an eTA to fly to Canada, just not a full visa.
A3: GR | B3: US | C3: Passport should be issued within the last 10 years. See Regional_Notes ('schengen'/'visa') for the shared 90-day short-stay rule and incoming ETIAS requirement — same across the whole Schengen Area, not Greece-specific. | D3: https://www.mfa.gr/usa/en/services/visas/ | E3: 2026-08-04 | F3: The Greek MFA visa page (mfa.gr) covers who needs a Schengen visa via a linked document rather than stating US status directly; kept as the country-specific official link, with the US State Dept page backing the shared Schengen rule in Regional_Notes.
A4: DE | B4: US | C4: Passport must have 2 blank pages; 6 months validity recommended though not strictly required. Amounts over 10,000 EUR (or equivalent) must be declared on both entry and exit. See Regional_Notes ('schengen'/'visa') for the shared 90-day short-stay rule and incoming ETIAS requirement. | D4: https://travel.state.gov/en/international-travel/travel-advisories/germany.html | E4: 2026-08-04 | F4: Same source page as the travel advisory. Note the same incoming ETIAS requirement flagged for Greece (Q4 2026) applies here too — it's Schengen-wide, not country-specific. | G4: Over 10,000 EUR (or equivalent) must be declared. Strict customs regulations on temporary import/export of firearms, WWII-era military artifacts, antiques, medications/pharmaceuticals, and business equipment. Illegal to bring in any literature, music, or items glorifying fascism, the Nazi past, or the "Third Reich." | H4: Over 10,000 EUR (or equivalent) must be declared. Same restrictions on military artifacts, antiques, and fascism-glorifying items apply on exit as on entry.
A5: BR | B5: US | C5: US citizens now require an e-visa to enter Brazil — Brazil reinstated this requirement on April 10, 2025, ending the prior visa-free arrangement. Apply online (about 15 minutes); processing takes roughly 10 working days, so apply at least 2 weeks ahead. Fee is $80.90, non-refundable. Once approved, the e-visa is valid up to 10 years with multiple entries, though each individual stay is capped at 90 days (extendable to 180 days total within any 12-month period). | D5: https://ie.utdallas.edu/?p=7739 | E5: 2026-08-04 | F5: This is a genuinely new requirement (April 2025) — worth double-checking status closer to any actual trip in case anything changes again. | I5: https://brazil.vfsevisa.com/
A6: IE | B6: US | C6: No visa required for US citizens for stays of 90 days or less. No minimum passport validity requirement (recommended: valid for the duration of stay), no vaccinations required. Note: Ireland is NOT a full Schengen member, so passport control applies even when arriving from a Schengen country. | D6: https://travel.state.gov/en/international-travel/travel-advisories/ireland.html | E6: 2026-08-05 | F6: Irish border officials have reportedly turned away US citizens who couldn't clearly explain their travel plans — worth having onward/return travel and accommodation details ready. | G6: Illegal to bring in marijuana/cannabis/CBD products or derivatives (fines, arrest, or detention possible). Illegal to bring in guns, ammunition, or even spent shell casings. | H6: Currency: amounts over 10,000 EUR (or equivalent) must be declared on exit, same as entry.
A61: LEGALLY SENSITIVE. official_url and last_verified are required on every row — never leave them blank.
A62: Requirements are PAIRWISE: they depend on the traveler's passport, not just the destination.
A63: Start with nationality_country_code = US only. The pairwise structure means adding others later needs no rework.
A64: The app must show the source link and the verified date. The summary is a pointer, never a substitute for the official source.

Sheet Advisories
A1: country_code | B1: issuing_authority | C1: level | D1: level_label | E1: summary | F1: official_url | G1: issued_date | H1: last_verified
A2: CA | B2: US State Department | C2: Level 1 | D2: Exercise Normal Precautions | E2: Standard precautions apply. Petty theft (purse snatching, car break-ins) occurs in tourist areas and big cities. Cyclonic winter storms and wildfires are noted seasonal risks. | F2: https://travel.state.gov/en/international-travel/travel-advisories/canada.html | G2: 2026-06-05 | H2: 2026-08-04
A3: GR | B3: US State Department | C3: Level 1 | D3: Exercise Normal Precautions | E3: Greece is a generally safe destination. Petty crime (pickpocketing, purse-snatching) occurs at popular tourist sites and on public transportation, especially the Athens metro. Large-scale demonstrations related to domestic politics can occur with little notice and may disrupt transportation. | F3: https://travel.state.gov/en/international-travel/travel-advisories/greece.html | G3: 2025-10-23 | H3: 2026-08-04
A4: DE | B4: US State Department | C4: Level 2 | D4: Exercise Increased Caution | E4: Elevated due to terrorism risk, consistent with the rest of Europe. Terrorist groups and radicalized individuals remain a persistent threat, targeting tourist locations, transit hubs, markets, and public events with little or no warning. Violent crime is otherwise rare — most incidents are pickpocketing at train stations and tourist spots. Demonstrations occur frequently and can disrupt transportation. | F4: https://travel.state.gov/en/international-travel/travel-advisories/germany.html | G4: 2025-05-13 | H4: 2026-08-04
A5: BR | B5: US State Department | C5: Level 2 | D5: Exercise Increased Caution | E5: Due to crime and kidnapping (kidnapping risk indicator specifically added). Violent crime — armed robbery, carjacking — occurs in urban areas day and night; a US traveler kidnapping-for-ransom incident was reported. Gang activity and organized crime are widespread, often tied to the drug trade. Drink-spiking/drugging assaults are common, especially in Rio de Janeiro, sometimes via dating apps or bars. Elevated Level 4 (Do Not Travel) zones: within 160km of the land borders with Bolivia, Colombia, Guyana, French Guiana, Paraguay, Peru, Suriname, and Venezuela, plus Brasília's Satellite Cities. | F5: https://travel.state.gov/content/travel/en/traveladvisories/traveladvisories/brazil-travel-advisory.html | G5: 2025-08-08 | H5: 2026-08-05
A6: IE | B6: US State Department | C6: Level 1 | D6: Exercise Normal Precautions | E6: Ireland is generally a safe destination. Petty crime — purse snatching, pickpocketing — is common in popular tourist locations; most crime against foreigners is opportunistic rather than violent. Large-scale demonstrations related to domestic politics can occur with little notice and may disrupt transportation. | F6: https://travel.state.gov/en/international-travel/travel-advisories/ireland.html | G6: 2026-03-20 | H6: 2026-08-05
A61: LEGALLY SENSITIVE + POLITICALLY LOADED. Always record and display the issuing authority.
A62: The US, UK, and Canadian governments frequently rate the same country differently.
A63: Multiple rows per country is intended and good — showing two or three assessments side by side is more honest
A64: than picking one and presenting it as neutral fact.
A65: Use the issuer's own wording for level and level_label. Don't normalize across governments — their scales differ.

Sheet Contributors
A1: contributor_id | B1: display_name | C1: relationship | D1: countries | E1: visited_when | F1: wants_credit | G1: contacted_on | H1: notes
A61: countries: comma-separated country codes they can speak to.
A62: visited_when matters — a friend's read on a country they saw in 2016 carries different weight than last year.
A63: wants_credit: ask on the form, let them choose their own display_name (first name, handle, whatever they prefer).
A64: Credit is country-level, not per-item — published content is your synthesis of several inputs.

Sheet Coverage
A1: Coverage Tracker
A2: Counts pull from the other sheets automatically. Add a row per country you're working on.
A4: country_code | B4: guide_items | C4: points_of_interest | D4: words | E4: phrases | F4: visa_rows | G4: advisory_rows | H4: ready?
A5: US | B5: =COUNTIF(Guide_Items!$B:$B,$A5) | C5: =COUNTIF(Explore!$B:$B,$A5) | D5: =COUNTIF(Words!$B:$B,$A5) | E5: =COUNTIF(Phrases!$B:$B,$A5) | F5: =COUNTIF(Visas!$A:$A,$A5) | G5: =COUNTIF(Advisories!$A:$A,$A5) | H5: =IF(AND(B5>=5,C5>=3,VLOOKUP($A5,Countries!$A:$I,9,FALSE)=TRUE,F5>=1,G5>=1),"ready (language N/A)",IF(AND(B5>=5,C5>=3,D5>=25,E5>=15,F5>=1,G5>=1),"ready","not yet"))
A6: GR | B6: =COUNTIF(Guide_Items!$B:$B,$A6) | C6: =COUNTIF(Explore!$B:$B,$A6) | D6: =COUNTIF(Words!$B:$B,$A6) | E6: =COUNTIF(Phrases!$B:$B,$A6) | F6: =COUNTIF(Visas!$A:$A,$A6) | G6: =COUNTIF(Advisories!$A:$A,$A6) | H6: =IF(AND(B6>=5,C6>=3,VLOOKUP($A6,Countries!$A:$I,9,FALSE)=TRUE,F6>=1,G6>=1),"ready (language N/A)",IF(AND(B6>=5,C6>=3,D6>=25,E6>=15,F6>=1,G6>=1),"ready","not yet"))
A7: GB | B7: =COUNTIF(Guide_Items!$B:$B,$A7) | C7: =COUNTIF(Explore!$B:$B,$A7) | D7: =COUNTIF(Words!$B:$B,$A7) | E7: =COUNTIF(Phrases!$B:$B,$A7) | F7: =COUNTIF(Visas!$A:$A,$A7) | G7: =COUNTIF(Advisories!$A:$A,$A7) | H7: =IF(AND(B7>=5,C7>=3,VLOOKUP($A7,Countries!$A:$I,9,FALSE)=TRUE,F7>=1,G7>=1),"ready (language N/A)",IF(AND(B7>=5,C7>=3,D7>=25,E7>=15,F7>=1,G7>=1),"ready","not yet"))
A8: IT | B8: =COUNTIF(Guide_Items!$B:$B,$A8) | C8: =COUNTIF(Explore!$B:$B,$A8) | D8: =COUNTIF(Words!$B:$B,$A8) | E8: =COUNTIF(Phrases!$B:$B,$A8) | F8: =COUNTIF(Visas!$A:$A,$A8) | G8: =COUNTIF(Advisories!$A:$A,$A8) | H8: =IF(AND(B8>=5,C8>=3,VLOOKUP($A8,Countries!$A:$I,9,FALSE)=TRUE,F8>=1,G8>=1),"ready (language N/A)",IF(AND(B8>=5,C8>=3,D8>=25,E8>=15,F8>=1,G8>=1),"ready","not yet"))
A9: ES | B9: =COUNTIF(Guide_Items!$B:$B,$A9) | C9: =COUNTIF(Explore!$B:$B,$A9) | D9: =COUNTIF(Words!$B:$B,$A9) | E9: =COUNTIF(Phrases!$B:$B,$A9) | F9: =COUNTIF(Visas!$A:$A,$A9) | G9: =COUNTIF(Advisories!$A:$A,$A9) | H9: =IF(AND(B9>=5,C9>=3,VLOOKUP($A9,Countries!$A:$I,9,FALSE)=TRUE,F9>=1,G9>=1),"ready (language N/A)",IF(AND(B9>=5,C9>=3,D9>=25,E9>=15,F9>=1,G9>=1),"ready","not yet"))
A10: IE | B10: =COUNTIF(Guide_Items!$B:$B,$A10) | C10: =COUNTIF(Explore!$B:$B,$A10) | D10: =COUNTIF(Words!$B:$B,$A10) | E10: =COUNTIF(Phrases!$B:$B,$A10) | F10: =COUNTIF(Visas!$A:$A,$A10) | G10: =COUNTIF(Advisories!$A:$A,$A10) | H10: =IF(AND(B10>=5,C10>=3,VLOOKUP($A10,Countries!$A:$I,9,FALSE)=TRUE,F10>=1,G10>=1),"ready (language N/A)",IF(AND(B10>=5,C10>=3,D10>=25,E10>=15,F10>=1,G10>=1),"ready","not yet"))
A11: GT | B11: =COUNTIF(Guide_Items!$B:$B,$A11) | C11: =COUNTIF(Explore!$B:$B,$A11) | D11: =COUNTIF(Words!$B:$B,$A11) | E11: =COUNTIF(Phrases!$B:$B,$A11) | F11: =COUNTIF(Visas!$A:$A,$A11) | G11: =COUNTIF(Advisories!$A:$A,$A11) | H11: =IF(AND(B11>=5,C11>=3,VLOOKUP($A11,Countries!$A:$I,9,FALSE)=TRUE,F11>=1,G11>=1),"ready (language N/A)",IF(AND(B11>=5,C11>=3,D11>=25,E11>=15,F11>=1,G11>=1),"ready","not yet"))
A12: NZ | B12: =COUNTIF(Guide_Items!$B:$B,$A12) | C12: =COUNTIF(Explore!$B:$B,$A12) | D12: =COUNTIF(Words!$B:$B,$A12) | E12: =COUNTIF(Phrases!$B:$B,$A12) | F12: =COUNTIF(Visas!$A:$A,$A12) | G12: =COUNTIF(Advisories!$A:$A,$A12) | H12: =IF(AND(B12>=5,C12>=3,VLOOKUP($A12,Countries!$A:$I,9,FALSE)=TRUE,F12>=1,G12>=1),"ready (language N/A)",IF(AND(B12>=5,C12>=3,D12>=25,E12>=15,F12>=1,G12>=1),"ready","not yet"))
A13: ID | B13: =COUNTIF(Guide_Items!$B:$B,$A13) | C13: =COUNTIF(Explore!$B:$B,$A13) | D13: =COUNTIF(Words!$B:$B,$A13) | E13: =COUNTIF(Phrases!$B:$B,$A13) | F13: =COUNTIF(Visas!$A:$A,$A13) | G13: =COUNTIF(Advisories!$A:$A,$A13) | H13: =IF(AND(B13>=5,C13>=3,VLOOKUP($A13,Countries!$A:$I,9,FALSE)=TRUE,F13>=1,G13>=1),"ready (language N/A)",IF(AND(B13>=5,C13>=3,D13>=25,E13>=15,F13>=1,G13>=1),"ready","not yet"))
A14: BR | B14: =COUNTIF(Guide_Items!$B:$B,$A14) | C14: =COUNTIF(Explore!$B:$B,$A14) | D14: =COUNTIF(Words!$B:$B,$A14) | E14: =COUNTIF(Phrases!$B:$B,$A14) | F14: =COUNTIF(Visas!$A:$A,$A14) | G14: =COUNTIF(Advisories!$A:$A,$A14) | H14: =IF(AND(B14>=5,C14>=3,VLOOKUP($A14,Countries!$A:$I,9,FALSE)=TRUE,F14>=1,G14>=1),"ready (language N/A)",IF(AND(B14>=5,C14>=3,D14>=25,E14>=15,F14>=1,G14>=1),"ready","not yet"))
A15: DE | B15: =COUNTIF(Guide_Items!$B:$B,$A15) | C15: =COUNTIF(Explore!$B:$B,$A15) | D15: =COUNTIF(Words!$B:$B,$A15) | E15: =COUNTIF(Phrases!$B:$B,$A15) | F15: =COUNTIF(Visas!$A:$A,$A15) | G15: =COUNTIF(Advisories!$A:$A,$A15) | H15: =IF(AND(B15>=5,C15>=3,VLOOKUP($A15,Countries!$A:$I,9,FALSE)=TRUE,F15>=1,G15>=1),"ready (language N/A)",IF(AND(B15>=5,C15>=3,D15>=25,E15>=15,F15>=1,G15>=1),"ready","not yet"))
A16: "ready" thresholds: 5+ guide items, 3+ landmarks, 25+ words, 15+ phrases, and at least one visa and advisory row. (Originally 8+ guide items, lowered to 5+ once real data showed 8 wasn't realistic for every country's natural content shape.)
A17: For countries with Countries!language_scope_na = TRUE (e.g. Canada), words/phrases minimums are skipped — the build-start trigger shouldn't wait on language content that was deliberately never meant to be complete.
A18: Adjust the formula in column H once you have a feel for what a genuinely useful country page needs.
A19: The example row (row 2) in each sheet is counted if its country_code matches — delete example rows before trusting these counts.

Sheet Regional_Notes
A1: group_slug | B1: note_type | C1: summary | D1: official_url | E1: last_verified
A2: schengen | B2: visa | C2: No visa required for US citizens for short stays up to 90 days in any 180-day period, across the entire Schengen Area. Starting Q4 2026, US citizens will also need to register for ETIAS (a low-cost online travel authorization, not a visa) before travel — not yet in effect as of this writing. Passport must be valid at least 3 months beyond planned departure. | D2: https://travel.state.gov/en/international-travel/planning/guidance/europe.html | E2: 2026-08-04
A4: group_slug: tag from Countries.regional_group (e.g. 'schengen'). note_type: 'visa' for now, extensible (e.g. 'advisory' if a shared regional risk pattern emerges).
A5: Country-specific Visa rows should keep only what's genuinely different per country (currency declaration thresholds, passport page requirements) and reference this table for the shared rule rather than restating it.

Sheet Languages
A1: country_code | B1: country_name | C1: language_code | D1: language_name | E1: is_official | F1: percent_speakers | G1: percent_year | H1: status | I1: source_url | J1: source_citation | K1: notes
A2: AF | B2: Afghanistan | C2: prs | D2: Dari | E2: TRUE | F2: 78 | G2: 2019 | H2: verified | I2: https://asiafoundation.org/publication/afghanistan-in-2019-a-survey-of-the-afghan-people/ | J2: Asia Foundation, Afghanistan in 2019: A Survey of the Afghan People, D-11 'Which languages do you speak?' (multiple response, n=15,930 adults)
A3: AF | B3: Afghanistan | C3: ps | D3: Pashto | E3: TRUE | F3: 50 | G3: 2019 | H3: verified | I3: https://asiafoundation.org/publication/afghanistan-in-2019-a-survey-of-the-afghan-people/ | J3: Asia Foundation, Afghanistan in 2019: A Survey of the Afghan People, D-11 (n=15,930)
A4: AF | B4: Afghanistan | C4: tk | D4: Turkmen | E4: TRUE | F4: 2 | G4: 2019 | H4: verified | I4: https://asiafoundation.org/publication/afghanistan-in-2019-a-survey-of-the-afghan-people/ | J4: Asia Foundation, Afghanistan in 2019: A Survey of the Afghan People, D-11 (n=15,930)
A5: AF | B5: Afghanistan | C5: uz | D5: Uzbek | E5: TRUE | F5: 10 | G5: 2019 | H5: verified | I5: https://asiafoundation.org/publication/afghanistan-in-2019-a-survey-of-the-afghan-people/ | J5: Asia Foundation, Afghanistan in 2019: A Survey of the Afghan People, D-11 (n=15,930)
A6: AF | B6: Afghanistan | C6: en | D6: English | E6: FALSE | F6: 5 | G6: 2019 | H6: verified | I6: https://asiafoundation.org/publication/afghanistan-in-2019-a-survey-of-the-afghan-people/ | J6: Asia Foundation, Afghanistan in 2019: A Survey of the Afghan People, D-11 (n=15,930)
A7: AX | B7: Åland Islands | C7: sv | D7: Swedish | E7: TRUE | H7: needs_research
A8: AX | B8: Åland Islands | C8: en | D8: English | E8: FALSE | H8: needs_research
A9: AL | B9: Albania | C9: sq | D9: Albanian | E9: TRUE | H9: needs_research
A10: AL | B10: Albania | C10: en | D10: English | E10: FALSE | H10: no_source
A11: DZ | B11: Algeria | C11: ar | D11: Arabic | E11: TRUE | H11: needs_research
A12: DZ | B12: Algeria | C12: en | D12: English | E12: FALSE | F12: 7 | H12: unverified | J12: Wikipedia, List of countries by English-speaking population (rev 1379399265), total speakers incl. second-language
A13: AS | B13: American Samoa | C13: en | D13: English | E13: TRUE | F13: 47.21 | H13: unverified | J13: Wikipedia, List of countries by English-speaking population (rev 1379399265), total speakers incl. second-language. Row note: 2020 U.S. Census{{cite web|title=DP2 SELECTED SOCIAL CHARACTERISTICS
A14: AS | B14: American Samoa | C14: sm | D14: Samoan | E14: TRUE | H14: needs_research
A15: AD | B15: Andorra | C15: ca | D15: Catalan | E15: TRUE | H15: needs_research
A16: AD | B16: Andorra | C16: en | D16: English | E16: FALSE | F16: 20.63 | H16: unverified | J16: Wikipedia, List of countries by English-speaking population (rev 1379399265), total speakers incl. second-language. Row note: Source Census: (Total speakers) Linguistic knowledge 2004, (Native speakers) Linguistic knowledge 2022. Cited: Grup de Sociologia; Govern d'Andorra
A17: AO | B17: Angola | C17: pt | D17: Portuguese | E17: TRUE | H17: needs_research
A18: AO | B18: Angola | C18: en | D18: English | E18: FALSE | H18: needs_research
A19: AI | B19: Anguilla | C19: en | D19: English | E19: TRUE | F19: 92.31 | H19: unverified | J19: Wikipedia, List of countries by English-speaking population (rev 1379399265), total speakers incl. second-language. Row note: Crystal (2003), p. 109.
A20: AQ | B20: Antarctica | C20: en | D20: English | E20: FALSE | H20: needs_research
A21: AG | B21: Antigua and Barbuda | C21: en | D21: English | E21: TRUE | F21: 80 | H21: unverified | J21: Wikipedia, List of countries by English-speaking population (rev 1379399265), total speakers incl. second-language. Row note: Crystal (2003), p. 109. This includes speakers of an English creole.
A22: AR | B22: Argentina | C22: gn | D22: Guaraní | E22: TRUE | H22: needs_research
A23: AR | B23: Argentina | C23: es | D23: Spanish | E23: TRUE | H23: needs_research
A24: AR | B24: Argentina | C24: en | D24: English | E24: FALSE | F24: 6.52 | H24: unverified | J24: Wikipedia, List of countries by English-speaking population (rev 1379399265), total speakers incl. second-language. Row note: Percentage of people who state they have a high level of English. Another 19.49% and 16.23% of people said they had an intermediate and low level, respectively, of English.. Cited: Página/12
A25: AM | B25: Armenia | C25: hy | D25: Armenian | E25: TRUE | H25: needs_research
A26: AM | B26: Armenia | C26: en | D26: English | E26: FALSE | F26: 4.93 | H26: unverified | J26: Wikipedia, List of countries by English-speaking population (rev 1379399265), total speakers incl. second-language. Row note: 2022 census, total count excludes 11,669 people who didn't answer question about language proficiency. All speakers were explicitly listed as second language speakers.. Cited: Statistical Committee - Republic of Armenia
A27: AW | B27: Aruba | C27: nl | D27: Dutch | E27: TRUE | H27: needs_research
A28: AW | B28: Aruba | C28: pap | D28: Papiamento | E28: TRUE | H28: needs_research
A29: AW | B29: Aruba | C29: en | D29: English | E29: FALSE | F29: 42.31 | H29: unverified | J29: Wikipedia, List of countries by English-speaking population (rev 1379399265), total speakers incl. second-language. Row note: Crystal (2003), p. 109.
A30: AU | B30: Australia | C30: en | D30: English | E30: TRUE | F30: 91.1 | H30: unverified | J30: Wikipedia, List of countries by English-speaking population (rev 1379399265), total speakers incl. second-language. Row note: The 2021 census data is subject to multiple interpretations. The data noted that 18,303,662 persons out of 23,401,892 total only spoke English, and a further 4,857,672 spoke English either "Very Well" or "Well". A further 872,213 persons we. Cited: Australian Bureau of Statistics
A31: AT | B31: Austria | C31: de | D31: German | E31: TRUE | F31: 98 | G31: 2023 | H31: verified | I31: https://europa.eu/eurobarometer/surveys/detail/2979 | J31: Special Eurobarometer 540 (2024), D48.alllang: mother tongue or spoken well enough to have a conversation, AT n=940, 15+
A32: AT | B32: Austria | C32: en | D32: English | E32: FALSE | F32: 59 | G32: 2023 | H32: verified | I32: https://europa.eu/eurobarometer/surveys/detail/2979 | J32: Special Eurobarometer 540 (2024), D48.alllang: mother tongue or spoken well enough to have a conversation, AT n=940, 15+
A33: AZ | B33: Azerbaijan | C33: az | D33: Azerbaijani | E33: TRUE | H33: needs_research
A34: AZ | B34: Azerbaijan | C34: ru | D34: Russian | E34: TRUE | H34: needs_research
A35: AZ | B35: Azerbaijan | C35: en | D35: English | E35: FALSE | F35: 1.29 | H35: unverified | J35: Wikipedia, List of countries by English-speaking population (rev 1379399265), total speakers incl. second-language. Row note: 2019 Census, excluded territories controlled by Republic of Artsakh at that time. Figures included only "the fluent speakers". They were all explicitly listed as second language speakers.. Cited: The State Statistical Committee of the Republic of Azerbaijan
A36: BS | B36: Bahamas | C36: en | D36: English | E36: TRUE | F36: 87.13 | H36: unverified | J36: Wikipedia, List of countries by English-speaking population (rev 1379399265), total speakers incl. second-language. Row note: Crystal (2003), p. 109. This includes speakers of an English creole.
A37: BH | B37: Bahrain | C37: ar | D37: Arabic | E37: TRUE | H37: needs_research
A38: BH | B38: Bahrain | C38: en | D38: English | E38: FALSE | H38: needs_research
A39: BD | B39: Bangladesh | C39: bn | D39: Bengali | E39: TRUE | H39: needs_research
A40: BD | B40: Bangladesh | C40: en | D40: English | E40: FALSE | F40: 6.53 | H40: unverified | J40: Wikipedia, List of countries by English-speaking population (rev 1379399265), total speakers incl. second-language. Row note: Population data are from 2022 Bangladeshi census, and second language data come from the subsequent survey. Cited: Daily Sun; Bangladesh Bureau of Statistics
A41: BB | B41: Barbados | C41: en | D41: English | E41: TRUE | F41: 100 | H41: unverified | J41: Wikipedia, List of countries by English-speaking population (rev 1379399265), total speakers incl. second-language. Row note: This includes speakers of an English creole.
A42: BY | B42: Belarus | C42: be | D42: Belarusian | E42: TRUE | H42: needs_research
A43: BY | B43: Belarus | C43: ru | D43: Russian | E43: TRUE | H43: needs_research
A44: BY | B44: Belarus | C44: en | D44: English | E44: FALSE | H44: no_source
A45: BE | B45: Belgium | C45: nl | D45: Dutch | E45: TRUE | F45: 63 | G45: 2023 | H45: verified | I45: https://europa.eu/eurobarometer/surveys/detail/2979 | J45: Special Eurobarometer 540 (2024), D48.alllang: mother tongue or spoken well enough to have a conversation, BE n=1001, 15+
A46: BE | B46: Belgium | C46: fr | D46: French | E46: TRUE | F46: 83 | G46: 2023 | H46: verified | I46: https://europa.eu/eurobarometer/surveys/detail/2979 | J46: Special Eurobarometer 540 (2024), D48.alllang: mother tongue or spoken well enough to have a conversation, BE n=1001, 15+
A47: BE | B47: Belgium | C47: de | D47: German | E47: TRUE | F47: 18 | G47: 2023 | H47: verified | I47: https://europa.eu/eurobarometer/surveys/detail/2979 | J47: Special Eurobarometer 540 (2024), D48.alllang: mother tongue or spoken well enough to have a conversation, BE n=1001, 15+
A48: BE | B48: Belgium | C48: en | D48: English | E48: FALSE | F48: 61 | G48: 2023 | H48: verified | I48: https://europa.eu/eurobarometer/surveys/detail/2979 | J48: Special Eurobarometer 540 (2024), D48.alllang: mother tongue or spoken well enough to have a conversation, BE n=1001, 15+
A49: BZ | B49: Belize | C49: bjz | D49: Belizean Creole | E49: TRUE | H49: needs_research
A50: BZ | B50: Belize | C50: en | D50: English | E50: TRUE | F50: 75.46 | H50: unverified | J50: Wikipedia, List of countries by English-speaking population (rev 1379399265), total speakers incl. second-language. Row note: 2022 Census Included population aged 4 or above who spoke English, no distinctions between first and second languages were made.. Cited: Statistical Institute of Belize
A51: BZ | B51: Belize | C51: es | D51: Spanish | E51: TRUE | H51: needs_research
A52: BJ | B52: Benin | C52: fr | D52: French | E52: TRUE | H52: needs_research
A53: BJ | B53: Benin | C53: en | D53: English | E53: FALSE | H53: needs_research
A54: BM | B54: Bermuda | C54: en | D54: English | E54: TRUE | F54: 96.92 | H54: unverified | J54: Wikipedia, List of countries by English-speaking population (rev 1379399265), total speakers incl. second-language. Row note: Crystal (2003), p. 109.
A55: BT | B55: Bhutan | C55: dz | D55: Dzongkha | E55: TRUE | H55: needs_research
A56: BT | B56: Bhutan | C56: en | D56: English | E56: FALSE | H56: needs_research
A57: BO | B57: Bolivia | C57: ay | D57: Aymara | E57: TRUE | H57: needs_research
A58: BO | B58: Bolivia | C58: gn | D58: Guaraní | E58: TRUE | H58: needs_research
A59: BO | B59: Bolivia | C59: qu | D59: Quechua | E59: TRUE | H59: needs_research
A60: BO | B60: Bolivia | C60: es | D60: Spanish | E60: TRUE | H60: needs_research
A61: BO | B61: Bolivia | C61: en | D61: English | E61: FALSE | H61: needs_research
A62: BA | B62: Bosnia and Herzegovina | C62: bs | D62: Bosnian | E62: TRUE | H62: needs_research
A63: BA | B63: Bosnia and Herzegovina | C63: hr | D63: Croatian | E63: TRUE | H63: needs_research
A64: BA | B64: Bosnia and Herzegovina | C64: sr | D64: Serbian | E64: TRUE | H64: needs_research
A65: BA | B65: Bosnia and Herzegovina | C65: en | D65: English | E65: FALSE | H65: no_source
A66: BW | B66: Botswana | C66: en | D66: English | E66: TRUE | F66: 38.42 | H66: unverified | J66: Wikipedia, List of countries by English-speaking population (rev 1379399265), total speakers incl. second-language. Row note: Crystal (2003), p. 109.
A67: BW | B67: Botswana | C67: tn | D67: Tswana | E67: TRUE | H67: needs_research
A68: BV | B68: Bouvet Island | C68: no | D68: Norwegian | E68: TRUE | H68: needs_research
A69: BV | B69: Bouvet Island | C69: en | D69: English | E69: FALSE | H69: needs_research
A70: BR | B70: Brazil | C70: pt | D70: Portuguese | E70: TRUE | H70: needs_research
A71: BR | B71: Brazil | C71: en | D71: English | E71: FALSE | F71: 5.56 | H71: unverified | J71: Wikipedia, List of countries by English-speaking population (rev 1379399265), total speakers incl. second-language. Row note: British council (2012) and EF. About 5% of Brazilians have a proficient grasp of English as a second or foreign additional language and an additional 6% have a very rudimentary knowledge.
A72: IO | B72: British Indian Ocean Territory | C72: en | D72: English | E72: TRUE | H72: needs_research
A73: VG | B73: British Virgin Islands | C73: en | D73: English | E73: TRUE | F73: 86.96 | H73: unverified | J73: Wikipedia, List of countries by English-speaking population (rev 1379399265), total speakers incl. second-language. Row note: Crystal (2003), p. 109. This includes speakers of an English creole.
A74: BN | B74: Brunei | C74: ms | D74: Malay | E74: TRUE | H74: needs_research
A75: BN | B75: Brunei | C75: en | D75: English | E75: FALSE | F75: 37.76 | H75: unverified | J75: Wikipedia, List of countries by English-speaking population (rev 1379399265), total speakers incl. second-language. Row note: Crystal (2003), p. 109.
A76: BG | B76: Bulgaria | C76: bg | D76: Bulgarian | E76: TRUE | F76: 98 | G76: 2023 | H76: verified | I76: https://europa.eu/eurobarometer/surveys/detail/2979 | J76: Special Eurobarometer 540 (2024), D48.alllang: mother tongue or spoken well enough to have a conversation, BG n=1034, 15+
A77: BG | B77: Bulgaria | C77: en | D77: English | E77: FALSE | F77: 30 | G77: 2023 | H77: verified | I77: https://europa.eu/eurobarometer/surveys/detail/2979 | J77: Special Eurobarometer 540 (2024), D48.alllang: mother tongue or spoken well enough to have a conversation, BG n=1034, 15+
A78: BF | B78: Burkina Faso | C78: fr | D78: French | E78: TRUE | H78: needs_research
A79: BF | B79: Burkina Faso | C79: en | D79: English | E79: FALSE | H79: needs_research
A80: BI | B80: Burundi | C80: fr | D80: French | E80: TRUE | H80: needs_research
A81: BI | B81: Burundi | C81: rn | D81: Kirundi | E81: TRUE | H81: needs_research
A82: BI | B82: Burundi | C82: en | D82: English | E82: FALSE | H82: no_source
A83: KH | B83: Cambodia | C83: km | D83: Khmer | E83: TRUE | H83: needs_research
A84: KH | B84: Cambodia | C84: en | D84: English | E84: FALSE | F84: 22.2 | H84: unverified | J84: Wikipedia, List of countries by English-speaking population (rev 1379399265), total speakers incl. second-language. Row note: Quote of a Ministry of Education spokesman. Cited: VOA Cambodia
A85: CM | B85: Cameroon | C85: en | D85: English | E85: TRUE | F85: 37.99 | H85: unverified | J85: Wikipedia, List of countries by English-speaking population (rev 1379399265), total speakers incl. second-language. Row note: Euromonitor International Report (2009)
A86: CM | B86: Cameroon | C86: fr | D86: French | E86: TRUE | H86: needs_research
A87: CA | B87: Canada | C87: en | D87: English | E87: TRUE | F87: 82.07 | H87: unverified | J87: Wikipedia, List of countries by English-speaking population (rev 1379399265), total speakers incl. second-language. Row note: The 2016 count reported that 23,757,525 people were able to conduct a conversation in English only, while 6,216,065 were able to converse in both English and French. The census also asked for the first language learned at home in childhood . Cited: Statcan.gc.ca
A88: CA | B88: Canada | C88: fr | D88: French | E88: TRUE | H88: needs_research
A89: CV | B89: Cape Verde | C89: pt | D89: Portuguese | E89: TRUE | H89: needs_research
A90: CV | B90: Cape Verde | C90: en | D90: English | E90: FALSE | H90: needs_research
A91: BQ | B91: Caribbean Netherlands | C91: nl | D91: Dutch | E91: TRUE | H91: needs_research
A92: BQ | B92: Caribbean Netherlands | C92: en | D92: English | E92: TRUE | F92: 80.31 | H92: unverified | J92: Wikipedia, List of countries by English-speaking population (rev 1379399265), total speakers incl. second-language. Population-weighted from the separate Bonaire, Sint Eustatius and Saba rows.
A93: BQ | B93: Caribbean Netherlands | C93: pap | D93: Papiamento | E93: TRUE | H93: needs_research
A94: KY | B94: Cayman Islands | C94: en | D94: English | E94: TRUE | F94: 88.75 | H94: unverified | J94: Wikipedia, List of countries by English-speaking population (rev 1379399265), total speakers incl. second-language. Row note: 2021 Census. Cited: Cayman Islands Government
A95: CF | B95: Central African Republic | C95: fr | D95: French | E95: TRUE | H95: needs_research
A96: CF | B96: Central African Republic | C96: sg | D96: Sango | E96: TRUE | H96: needs_research
A97: CF | B97: Central African Republic | C97: en | D97: English | E97: FALSE | H97: needs_research
A98: TD | B98: Chad | C98: ar | D98: Arabic | E98: TRUE | H98: needs_research
A99: TD | B99: Chad | C99: fr | D99: French | E99: TRUE | H99: needs_research
A100: TD | B100: Chad | C100: en | D100: English | E100: FALSE | H100: needs_research
...
